{
    "response": [
        {
            "maintainer": "Jacoa",
            "oem": "Google",
            "device": "Pixel 6",
            "filename": "crDroidAndroid-16.0-20260102-oriole-v12.5.zip",
            "download": "https://github.com/JacoaFur/ota/releases/download/20260102/crDroidAndroid-16.0-20260102-oriole-v12.5.zip",
            "timestamp": 1767333927,
            "md5": "018adde853dbe8a327e6aa0ae2c0b357",
            "sha256": "886d9ed543edf3a5fa92c5cf9d039387362191749d01e19ca6cb4d2c320908e3",
            "size": 1425103975,
            "version": "12.5",
            "buildtype": "Unofficial",
            "forum": "",
            "gapps": "https://nikgapps.com/ionutgherman",
            "firmware": "",
            "modem": "",
            "bootloader": "",
            "recovery": "https://drive.google.com/file/d/1Lwj1Tozm2vFsvJ-2TVhei8ufR474hdg6",
            "paypal": "",
            "telegram": "https://t.me/jacoa",
            "dt": "https://github.com/LineageOS/android_device_google_raviole",
            "common-dt": "https://github.com/LineageOS/android_device_google_gs101",
            "kernel": "https://github.com/LineageOS/android_device_google_raviole-kernels"
        }
    ]
}
